<?xml version="1.0" encoding="UTF-8"?>
<!DOCTYPE suite SYSTEM "https://testng.org/testng-1.0.dtd">
<suite name="Suite" thread-count="5">
<listeners>
    <listener class-name="Utilities.ExtentTestListener"/>
</listeners>

<parameter name="OS" value="Windows"></parameter>
<parameter name="browser" value="Chrome"></parameter>
  <test thread-count="5" name="Test">
    <classes>
       <class name="testCases.TC01_AccountRegister"/>
       <class name="testCases.TC02_AccountLogin"/>
       <class name="testCases.TC03_AccountLoginMultipleLoginData"/>
       <class name="testCases.TC04_HomePageUI"/>

    </classes>
  </test> <!-- Test -->
</suite> <!-- Suite -->
